yogymax/__init__.py
yogymax/sample.py
yogy_pkg_yogymax-1.0.1.dist-info/LICENSE
yogy_pkg_yogymax-1.0.1.dist-info/METADATA
yogy_pkg_yogymax-1.0.1.dist-info/WHEEL
yogy_pkg_yogymax-1.0.1.dist-info/top_level.txt
yogy_pkg_yogymax-1.0.1.dist-info/RECORD
